workerqueue/__init__.py
workerqueue/_workerqueue.py
workerqueue-0.0.2.dist-info/METADATA
workerqueue-0.0.2.dist-info/WHEEL
workerqueue-0.0.2.dist-info/top_level.txt
workerqueue-0.0.2.dist-info/RECORD
