Metadata-Version: 2.1
Name: workerqueue
Version: 0.0.2
Summary: A thread-based worker queue
Home-page: https://github.com/jaeseopark/workerqueue
Author: Jaeseo Park
License: UNKNOWN
Platform: UNKNOWN
Classifier: Programming Language :: Python :: 3
Classifier: Operating System :: OS Independent
Requires-Python: >=3
